COPYING
MANIFEST.in
README
setup.py
django_memorize.egg-info/PKG-INFO
django_memorize.egg-info/SOURCES.txt
django_memorize.egg-info/dependency_links.txt
django_memorize.egg-info/top_level.txt
memorize/__init__.py
memorize/algorithm.py
memorize/forms.py
memorize/models.py
memorize/views.py