Metadata-Version: 1.0
Name: django-memorize
Version: 0.5.1
Summary: Memorize your Django project's items with spaced repetition theory
Home-page: http://code.google.com/p/django-memorize/
Author: Cristian Esquivias
Author-email: cristian.esquivias@gmail.com
License: UNKNOWN
Platform: UNKNOWN
Classifier: Development Status :: 4 - Beta
Classifier: Environment :: Web Environment
Classifier: Framework :: Django
Classifier: Intended Audience :: Developers
Classifier: Intended Audience :: Education
Classifier: License :: OSI Approved :: GNU General Public License (GPL)
Classifier: Natural Language :: English
Classifier: Operating System :: OS Independent
Classifier: Programming Language :: Python :: 2
Classifier: Topic :: Education
Classifier: Topic :: Software Development :: Libraries :: Python Modules
